new_destiny/__init__.py
new_destiny/rate_limit_exceptions.py
new_destiny/rate_limit_helpers.py
new_destiny/rate_limiter.py
new_destiny/riot_get_request.py
new_destiny/riot_get_request_with_retry.py
new_destiny/settings/config.py
new_destiny/utilities.py
new_destiny-0.2.6.dist-info/METADATA
new_destiny-0.2.6.dist-info/WHEEL
new_destiny-0.2.6.dist-info/licenses/LICENSE
new_destiny-0.2.6.dist-info/RECORD
