Metadata-Version: 2.4
Name: new-destiny
Version: 0.2.6
Summary: An easy to use, fully async, fast, scalable, interpretable rate limiting solution for the Riot Games API (currently for League of Legends only) built on Python, asyncio, and Redis.
License: MIT
License-File: LICENSE
Author: Victor Haynes
Author-email: vichaynesdevelopment@gmail.com
Requires-Python: >=3.13,<4.0
Classifier: License :: OSI Approved :: MIT License
Classifier: Programming Language :: Python :: 3
Classifier: Programming Language :: Python :: 3.13
Classifier: Programming Language :: Python :: 3.14
Requires-Dist: anyio (==4.9.0)
Requires-Dist: cachecontrol (==0.14.3)
Requires-Dist: certifi (==2025.4.26)
Requires-Dist: cffi (==1.17.1)
Requires-Dist: charset-normalizer (==3.4.2)
Requires-Dist: colorama (==0.4.6)
Requires-Dist: dotenv (==0.9.9)
Requires-Dist: dulwich (==0.22.8)
Requires-Dist: fastjsonschema (==2.21.1)
Requires-Dist: filelock (==3.18.0)
Requires-Dist: h11 (==0.16.0)
Requires-Dist: httpcore (==1.0.9)
Requires-Dist: httpx (==0.28.1)
Requires-Dist: idna (==3.10)
Requires-Dist: keyring (==25.6.0)
Requires-Dist: more-itertools (==10.7.0)
Requires-Dist: msgpack (==1.1.0)
Requires-Dist: packaging (==25.0)
Requires-Dist: platformdirs (==4.3.8)
Requires-Dist: pycparser (==2.22)
Requires-Dist: python-dotenv (==1.1.0)
Requires-Dist: rapidfuzz (==3.13.0)
Requires-Dist: redis (==6.1.0)
Requires-Dist: requests (==2.32.3)
Requires-Dist: requests-toolbelt (==1.0.0)
Requires-Dist: sniffio (==1.3.1)
Requires-Dist: sortedcontainers (==2.4.0)
Requires-Dist: urllib3 (==2.4.0)
Requires-Dist: xattr (==1.1.4)
Requires-Dist: zstandard (==0.23.0)
